spenv.py
spenv-0.1.1.dist-info/LICENSE
spenv-0.1.1.dist-info/METADATA
spenv-0.1.1.dist-info/WHEEL
spenv-0.1.1.dist-info/RECORD
